{
  "ComponentIndexes": {
    "CustomCalendar": 4
  },
  "ControlUniqueGuids": {},
  "ControlUniqueIds": {
    "ABV_DataCard1": 149,
    "ABV_DataCard2": 43,
    "Add_Icon": 266,
    "ALC_lbl": 252,
    "ALC_value": 263,
    "App": 1,
    "Attachments_DataCard2": 286,
    "Barcode_DataCard1": 139,
    "Barcode_DataCard2": 48,
    "Bottle_DataCard1": 164,
    "Bottle_DataCard2": 53,
    "Btl/Ctn_DataCard1": 154,
    "Btl/Ctn_DataCard2": 58,
    "btnSetYearMonth": 22,
    "Button1": 184,
    "Button2": 188,
    "Button3": 189,
    "Button4": 291,
    "Carton_Quantity_vlaue": 264,
    "Checkbox1": 230,
    "Checkbox1_1": 232,
    "ComboBox1": 220,
    "Contact_DataCard1": 204,
    "Contact_DataCard2": 94,
    "Container3": 219,
    "CQ_Label": 257,
    "Create Date_DataCard1": 63,
    "Currency_lbl": 244,
    "Currency_value": 250,
    "CustomCalendar": 3,
    "Customer Lead Id_DataCard1": 201,
    "Customer Lead Id_DataCard2": 117,
    "Customer Lead Id_DataCard3": 99,
    "DataCardKey1": 205,
    "DataCardKey10": 60,
    "DataCardKey11": 64,
    "DataCardKey12": 68,
    "DataCardKey13": 76,
    "DataCardKey14": 81,
    "DataCardKey15": 120,
    "DataCardKey16": 132,
    "DataCardKey17": 124,
    "DataCardKey18": 136,
    "DataCardKey19": 156,
    "DataCardKey2": 30,
    "DataCardKey20": 151,
    "DataCardKey21": 141,
    "DataCardKey22": 166,
    "DataCardKey23": 176,
    "DataCardKey24": 161,
    "DataCardKey25": 171,
    "DataCardKey27": 86,
    "DataCardKey28": 91,
    "DataCardKey29": 96,
    "DataCardKey3": 35,
    "DataCardKey30": 101,
    "DataCardKey31": 146,
    "DataCardKey37": 283,
    "DataCardKey38": 288,
    "DataCardKey4": 202,
    "DataCardKey5": 211,
    "DataCardKey6": 40,
    "DataCardKey7": 45,
    "DataCardKey8": 50,
    "DataCardKey9": 55,
    "DataCardValue1": 31,
    "DataCardValue10": 82,
    "DataCardValue11": 87,
    "DataCardValue12": 92,
    "DataCardValue13": 97,
    "DataCardValue15": 126,
    "DataCardValue16": 137,
    "DataCardValue17": 157,
    "DataCardValue18": 152,
    "DataCardValue19": 142,
    "DataCardValue2": 36,
    "DataCardValue20": 167,
    "DataCardValue21": 177,
    "DataCardValue22": 162,
    "DataCardValue23": 172,
    "DataCardValue25": 102,
    "DataCardValue26": 147,
    "DataCardValue3": 41,
    "DataCardValue32": 284,
    "DataCardValue33": 289,
    "DataCardValue4": 46,
    "DataCardValue5": 51,
    "DataCardValue6": 56,
    "DataCardValue7": 61,
    "DataCardValue8": 65,
    "DataCardValue9": 77,
    "DateValue1": 212,
    "DateValue2": 133,
    "DateValue3": 69,
    "ddMonth": 21,
    "ddYear": 20,
    "Decoded_CB": 260,
    "Decoded_Lbl": 253,
    "Description_DataCard1": 33,
    "Description_DataCard2": 122,
    "Edit_icon": 271,
    "ErrorMessage1": 32,
    "ErrorMessage10": 78,
    "ErrorMessage11": 83,
    "ErrorMessage12": 88,
    "ErrorMessage13": 118,
    "ErrorMessage14": 130,
    "ErrorMessage15": 125,
    "ErrorMessage16": 138,
    "ErrorMessage17": 158,
    "ErrorMessage18": 153,
    "ErrorMessage19": 143,
    "ErrorMessage2": 37,
    "ErrorMessage20": 168,
    "ErrorMessage21": 178,
    "ErrorMessage22": 163,
    "ErrorMessage23": 173,
    "ErrorMessage25": 93,
    "ErrorMessage26": 98,
    "ErrorMessage27": 103,
    "ErrorMessage28": 148,
    "ErrorMessage3": 42,
    "ErrorMessage34": 285,
    "ErrorMessage35": 290,
    "ErrorMessage4": 209,
    "ErrorMessage5": 47,
    "ErrorMessage6": 52,
    "ErrorMessage7": 57,
    "ErrorMessage8": 62,
    "ErrorMessage9": 73,
    "Expiry Date_DataCard1": 207,
    "Expiry Date_DataCard2": 127,
    "Expiry Date_DataCard3": 66,
    "Form1": 200,
    "Form2": 116,
    "Form3": 27,
    "Form5": 280,
    "Frame": 12,
    "FrameShadow": 17,
    "Gallery1": 269,
    "Gallery2": 179,
    "Gallery3": 104,
    "galleryTemplate1": 270,
    "galleryTemplate1_4": 10,
    "galleryTemplate2": 180,
    "galleryTemplate2_1": 14,
    "galleryTemplate3": 105,
    "Group1": 294,
    "Header Label_1": 196,
    "Header Label_2": 112,
    "Header_1": 293,
    "Home Screen": 185,
    "Home_Icon": 198,
    "Home_Icon_1": 114,
    "HourValue1": 70,
    "Icon1": 242,
    "Icon2": 182,
    "Icon2_1": 183,
    "Icon3": 272,
    "iconNextMonth": 7,
    "iconPrevMonth": 6,
    "Image1": 186,
    "Image2": 187,
    "Image3": 191,
    "Image4": 106,
    "Image5": 113,
    "Item No_DataCard1": 134,
    "Item No_DataCard2": 38,
    "Label1": 190,
    "Label2": 221,
    "Label2_1": 223,
    "Label2_10": 240,
    "Label2_2": 225,
    "Label2_3": 227,
    "Label2_4": 229,
    "Label2_5": 231,
    "Label2_6": 233,
    "Label2_7": 235,
    "Label2_8": 237,
    "Label2_9": 239,
    "Label3": 268,
    "Label4": 251,
    "Label4_26": 215,
    "Label4_36": 217,
    "Label4_38": 214,
    "Label5": 181,
    "Label6": 115,
    "Label7": 213,
    "Label8": 199,
    "Label9": 267,
    "lblMonth": 19,
    "LblMonthSelected": 5,
    "lblYear": 18,
    "Litres_lbl": 254,
    "Litres_Value": 262,
    "Logo_1": 197,
    "Lt/Btl_DataCard1": 174,
    "Lt/Btl_DataCard2": 74,
    "Max Price (ntz_maxprice)_DataCard1": 79,
    "Max Price_DataCard1": 159,
    "Maxprice_lbl": 218,
    "MaxPrice_value": 249,
    "Min Price (ntz_minprice)_DataCard1": 84,
    "Min Price_DataCard1": 169,
    "MinPrice_lbl": 243,
    "MinPrice_value": 248,
    "MinuteValue1": 129,
    "MinuteValue2": 72,
    "ModelDrivenFormIntegration": 25,
    "MonthDayGallery": 13,
    "Name_DataCard1": 28,
    "NextArrow1": 108,
    "NonRefiil_CB": 259,
    "Non-refill_lbl": 255,
    "Prodcut_lbl": 216,
    "Product _Code": 261,
    "Productcode_lbl": 256,
    "ProductList_CB": 247,
    "Quantity_DataCard1": 144,
    "Quantity_lbl": 245,
    "Quantity_value": 246,
    "Rectangle1": 193,
    "Rectangle1_1": 4,
    "Rectangle2": 195,
    "Rectangle3": 292,
    "Rectangle5": 194,
    "SaveButton": 279,
    "Screen_AddNewCustomerTargetPricing": 192,
    "Screen_ViewCustomerTargetPricing": 111,
    "Screen1": 26,
    "Separator1": 208,
    "Separator2": 128,
    "Separator3": 71,
    "Separator4": 110,
    "SetDefaultTimer": 23,
    "StarVisible1": 29,
    "StarVisible10": 75,
    "StarVisible11": 80,
    "StarVisible12": 85,
    "StarVisible13": 119,
    "StarVisible14": 131,
    "StarVisible15": 123,
    "StarVisible16": 135,
    "StarVisible17": 155,
    "StarVisible18": 150,
    "StarVisible19": 140,
    "StarVisible2": 34,
    "StarVisible20": 165,
    "StarVisible21": 175,
    "StarVisible22": 160,
    "StarVisible23": 170,
    "StarVisible25": 90,
    "StarVisible26": 95,
    "StarVisible27": 100,
    "StarVisible28": 145,
    "StarVisible3": 39,
    "StarVisible34": 282,
    "StarVisible35": 287,
    "StarVisible4": 210,
    "StarVisible5": 44,
    "StarVisible6": 49,
    "StarVisible7": 54,
    "StarVisible8": 59,
    "StarVisible9": 67,
    "Subcircle1_1": 16,
    "Subtitle1": 109,
    "TextInput1": 222,
    "TextInput1_1": 224,
    "TextInput1_2": 226,
    "TextInput1_3": 228,
    "TextInput1_4": 234,
    "TextInput1_5": 236,
    "TextInput1_6": 238,
    "TextInput1_7": 241,
    "TextInput12": 275,
    "TextInput13": 276,
    "TextInput14": 278,
    "TextInput15": 277,
    "TextInput2": 273,
    "TextInput3": 203,
    "TextInput4": 206,
    "TextInput5": 274,
    "TextInput6": 121,
    "Title_DataCard1": 281,
    "Title1": 107,
    "Title1_1": 11,
    "Title2_4": 15,
    "TodayIcon": 8,
    "Variant_DataCard1": 89,
    "Variant_value": 265,
    "Varient_label": 258,
    "WeekdayGallery": 9,
    "YearMonthPicker": 24
  },
  "FunctionParamsInvariantScripts": {},
  "FunctionParamsInvariantScriptsOnInstances": {},
  "HeaderLastSavedDateTimeUTC": "01/03/2023 11:16:55",
  "IsLegacyComponentAllowGlobalScopeCase": false,
  "LocalConnectionIDReferences": {
    "592d4f51-6b18-4e5e-95a9-c6bfed89113c": "\"/providers/microsoft.powerapps/apis/shared_excelonlinebusiness/connections/shared-excelonlinebu-0ee4e134-c547-4b27-a12b-bdcc348f4d25\"",
    "da5913c3-4335-450f-8ab9-c25ed7aa33e3": "\"/providers/microsoft.powerapps/apis/shared_logicflows/connections/7dae44c6192b48c4ae31043b2a88d0fe-c8c59f0b20851dda\"",
    "df4281c0-e0a4-49f7-9d94-20b3d42bd4f3": "\"/providers/microsoft.powerapps/apis/shared_sql/connections/e53bf8da15304ddf9d52466baa8ce6e1\"",
    "f3d9070f-381e-4a91-916f-c9ad3af0d19a": "\"/providers/microsoft.powerapps/apis/shared_sharepointonline/connections/21dc9c9140e64c68b0f82cc61a5c48c1\""
  },
  "LocalDatabaseReferencesAsEmpty": false,
  "LocalResourceFileNames": {
    "Bacardi-hpb": "0001.jpg",
    "Craft-Beer": "0002.jpg",
    "decorative-green-color-modern-geometric-stripes-transparent-background-vector_1055-12665 (1)": "0003.jpg",
    "download": "0004.png",
    "Kollaras_and_Co": "0005.png",
    "Mogul-Banner": "0006.jpg",
    "OIP": "0008.jpeg",
    "OIP (5)": "0007.jpeg",
    "Peroni": "0009.jpg",
    "PowerAddictWaterMark": "05c97645-52de-4776-b610-97f511d4b6d9.jpg",
    "PowerAddictWaterMark1": "b88b2826-2f74-4f37-9855-13d8638dd1a6.jpg"
  },
  "LocalResourceRootPaths": {
    "Bacardi-hpb": "https://docserverpwaprodseau.blob.core.windows.net/b256725e-1931-47aa-b8e1-c08ef1aa9d3e-1/resource/Assets0Images00001.jpg?sv=2017-04-17&sr=b&sig=BHJKowqAR%2FUG9EMyYjJcd60hSEiZP3Lu%2BbQb93%2FQie8%3D&spr=https&se=2023-01-04T11%3A25%3A48Z&sp=r",
    "Craft-Beer": "https://docserverpwaprodseau.blob.core.windows.net/b256725e-1931-47aa-b8e1-c08ef1aa9d3e-1/resource/Assets0Images00002.jpg?sv=2017-04-17&sr=b&sig=dzDV6TVOYbsQXuh0BZUmZdYX%2F4q0Ew874pIkUivi9Ec%3D&spr=https&se=2023-01-04T11%3A25%3A48Z&sp=r",
    "decorative-green-color-modern-geometric-stripes-transparent-background-vector_1055-12665 (1)": "https://docserverpwaprodseau.blob.core.windows.net/b256725e-1931-47aa-b8e1-c08ef1aa9d3e-1/resource/Assets0Images00003.jpg?sv=2017-04-17&sr=b&sig=acHvXcomIxkSCukm%2FL5%2BzevGm%2BXyOwgYZIlEYFSTZjQ%3D&spr=https&se=2023-01-04T11%3A25%3A48Z&sp=r",
    "download": "https://docserverpwaprodseau.blob.core.windows.net/b256725e-1931-47aa-b8e1-c08ef1aa9d3e-1/resource/Assets0Images00004.png?sv=2017-04-17&sr=b&sig=ZM1rqC6Yfhhlo%2BSfuriiF2wQlecnTIKsNQANq9nrwdA%3D&spr=https&se=2023-01-04T11%3A25%3A48Z&sp=r",
    "Kollaras_and_Co": "https://docserverpwaprodseau.blob.core.windows.net/b256725e-1931-47aa-b8e1-c08ef1aa9d3e-1/resource/Assets0Images00005.png?sv=2017-04-17&sr=b&sig=0wrQGpot1lOmyvBZ6IHaKG2OutLHXcVURALUT9ggsrc%3D&spr=https&se=2023-01-04T11%3A25%3A48Z&sp=r",
    "Mogul-Banner": "https://docserverpwaprodseau.blob.core.windows.net/b256725e-1931-47aa-b8e1-c08ef1aa9d3e-1/resource/Assets0Images00006.jpg?sv=2017-04-17&sr=b&sig=wIarRr75aekaAvuIjzjmia%2Fze1scvnxvxPdAGlGSuXw%3D&spr=https&se=2023-01-04T11%3A25%3A48Z&sp=r",
    "OIP": "https://docserverpwaprodseau.blob.core.windows.net/b256725e-1931-47aa-b8e1-c08ef1aa9d3e-1/resource/Assets0Images00008.jpeg?sv=2017-04-17&sr=b&sig=Ax5G4%2FHGQgFSWu3jZbMXAcEPb9rLSGvpJ2XY8oKvBd4%3D&spr=https&se=2023-01-04T11%3A25%3A48Z&sp=r",
    "OIP (5)": "https://docserverpwaprodseau.blob.core.windows.net/b256725e-1931-47aa-b8e1-c08ef1aa9d3e-1/resource/Assets0Images00007.jpeg?sv=2017-04-17&sr=b&sig=fnOAb%2FylQk8zoFZufEwOrPbIBOSwOzqOgdLWy2%2Br6Rw%3D&spr=https&se=2023-01-04T11%3A25%3A48Z&sp=r",
    "Peroni": "https://docserverpwaprodseau.blob.core.windows.net/b256725e-1931-47aa-b8e1-c08ef1aa9d3e-1/resource/Assets0Images00009.jpg?sv=2017-04-17&sr=b&sig=eEwCD0dXang%2BvKrFLRm7WvsBkMygqdNr8o8wGq3vqMI%3D&spr=https&se=2023-01-04T11%3A25%3A48Z&sp=r",
    "PowerAddictWaterMark": "https://docserverpwaprodseau.blob.core.windows.net/b256725e-1931-47aa-b8e1-c08ef1aa9d3e-1/resource/Assets0Images005c97645-52de-4776-b610-97f511d4b6d9.jpg?sv=2017-04-17&sr=b&sig=9GPPLPrTF08hBB9v8jWhFXhaF38HGAWW42GgHFa49J8%3D&spr=https&se=2023-01-04T11%3A25%3A48Z&sp=r",
    "PowerAddictWaterMark1": "https://docserverpwaprodseau.blob.core.windows.net/b256725e-1931-47aa-b8e1-c08ef1aa9d3e-1/resource/Assets0Images0b88b2826-2f74-4f37-9855-13d8638dd1a6.jpg?sv=2017-04-17&sr=b&sig=0jAWdoQlLZyELDWSdO%2F88SChPwKUGu2He1zMTySqIyM%3D&spr=https&se=2023-01-04T11%3A25%3A48Z&sp=r"
  },
  "OrderComponentMetadata": {
    "839baf53ea1543f795c43431334252fa": 0
  },
  "OrderComponentTemplate": {
    "839baf53ea1543f795c43431334252fa": 0
  },
  "OrderDataSource": {
    "Accounts": 142,
    "Accounts\\account_accountcategorycode": 19,
    "Accounts\\account_accountclassificationcode": 22,
    "Accounts\\account_accountratingcode": 32,
    "Accounts\\account_address1_addresstypecode": 17,
    "Accounts\\account_address1_freighttermscode": 20,
    "Accounts\\account_address1_shippingmethodcode": 18,
    "Accounts\\account_address2_addresstypecode": 33,
    "Accounts\\account_address2_freighttermscode": 25,
    "Accounts\\account_address2_shippingmethodcode": 35,
    "Accounts\\account_businesstypecode": 29,
    "Accounts\\account_creditonhold": 2,
    "Accounts\\account_customersizecode": 23,
    "Accounts\\account_customertypecode": 34,
    "Accounts\\account_donotbulkemail": 5,
    "Accounts\\account_donotbulkpostalmail": 3,
    "Accounts\\account_donotemail": 8,
    "Accounts\\account_donotfax": 6,
    "Accounts\\account_donotphone": 13,
    "Accounts\\account_donotpostalmail": 7,
    "Accounts\\account_donotsendmm": 1,
    "Accounts\\account_followemail": 11,
    "Accounts\\account_industrycode": 28,
    "Accounts\\account_isprivate": 10,
    "Accounts\\account_marketingonly": 9,
    "Accounts\\account_merged": 12,
    "Accounts\\account_ownershipcode": 24,
    "Accounts\\account_participatesinworkflow": 15,
    "Accounts\\account_paymenttermscode": 31,
    "Accounts\\account_preferredappointmentdaycode": 36,
    "Accounts\\account_preferredappointmenttimecode": 21,
    "Accounts\\account_preferredcontactmethodcode": 27,
    "Accounts\\account_shippingmethodcode": 30,
    "Accounts\\account_statecode": 39,
    "Accounts\\account_statuscode": 40,
    "Accounts\\account_territorycode": 37,
    "Accounts\\cdi_account_cdi_allowtextmessages": 4,
    "Accounts\\default.cds_account_views": 129,
    "Accounts\\kol_account_kol_blocked": 14,
    "Accounts\\kol_responsibilitycentre": 26,
    "Accounts\\kol_segmentoptions": 38,
    "Accounts\\msdyn_account_msdyn_gdproptout": 16,
    "ComboBoxSample": 134,
    "Contacts": 143,
    "Contacts\\cdi_contact_cdi_allowtextmessages": 57,
    "Contacts\\contact_accountrolecode": 67,
    "Contacts\\contact_address1_addresstypecode": 62,
    "Contacts\\contact_address1_freighttermscode": 60,
    "Contacts\\contact_address1_shippingmethodcode": 74,
    "Contacts\\contact_address2_addresstypecode": 76,
    "Contacts\\contact_address2_freighttermscode": 64,
    "Contacts\\contact_address2_shippingmethodcode": 77,
    "Contacts\\contact_address3_addresstypecode": 78,
    "Contacts\\contact_address3_freighttermscode": 69,
    "Contacts\\contact_address3_shippingmethodcode": 75,
    "Contacts\\contact_creditonhold": 45,
    "Contacts\\contact_customersizecode": 71,
    "Contacts\\contact_customertypecode": 59,
    "Contacts\\contact_donotbulkemail": 47,
    "Contacts\\contact_donotbulkpostalmail": 42,
    "Contacts\\contact_donotemail": 56,
    "Contacts\\contact_donotfax": 52,
    "Contacts\\contact_donotphone": 54,
    "Contacts\\contact_donotpostalmail": 43,
    "Contacts\\contact_donotsendmm": 46,
    "Contacts\\contact_educationcode": 81,
    "Contacts\\contact_familystatuscode": 79,
    "Contacts\\contact_followemail": 48,
    "Contacts\\contact_gendercode": 61,
    "Contacts\\contact_haschildrencode": 58,
    "Contacts\\contact_isautocreate": 55,
    "Contacts\\contact_isbackofficecustomer": 41,
    "Contacts\\contact_isprivate": 53,
    "Contacts\\contact_leadsourcecode": 73,
    "Contacts\\contact_marketingonly": 51,
    "Contacts\\contact_merged": 50,
    "Contacts\\contact_msdyn_orgchangestatus": 65,
    "Contacts\\contact_participatesinworkflow": 49,
    "Contacts\\contact_paymenttermscode": 66,
    "Contacts\\contact_preferredappointmentdaycode": 70,
    "Contacts\\contact_preferredappointmenttimecode": 63,
    "Contacts\\contact_preferredcontactmethodcode": 72,
    "Contacts\\contact_shippingmethodcode": 80,
    "Contacts\\contact_statecode": 82,
    "Contacts\\contact_statuscode": 83,
    "Contacts\\contact_territorycode": 68,
    "Contacts\\default.cds_contact_views": 130,
    "Contacts\\msdyn_contact_msdyn_gdproptout": 44,
    "Currencies": 144,
    "Currencies\\default.cds_transactioncurrency_views": 131,
    "Currencies\\transactioncurrency_statecode": 84,
    "Currencies\\transactioncurrency_statuscode": 85,
    "Customer Target Pricing": 145,
    "Customer Target Pricing Deploy List": 135,
    "Customer Target Pricing\\default.cds_ntz_customertargetpricing_views": 132,
    "Customer Target Pricing\\ntz_customertargetpricing_ntz_decoded": 87,
    "Customer Target Pricing\\ntz_customertargetpricing_ntz_nonrefill": 86,
    "Customer Target Pricing\\ntz_customertargetpricing_statecode": 88,
    "Customer Target Pricing\\ntz_customertargetpricing_statuscode": 89,
    "CustomGallerySample": 136,
    "DropDownSample": 137,
    "flowExcelData": 147,
    "GetExcelData": 0,
    "Leads": 146,
    "Leads\\budgetstatus": 106,
    "Leads\\cdi_lead_cdi_allowtextmessages": 96,
    "Leads\\confirminterest": 98,
    "Leads\\decisionmaker": 99,
    "Leads\\default.cds_lead_views": 133,
    "Leads\\evaluatefit": 93,
    "Leads\\initialcommunication": 110,
    "Leads\\kol_lead_kol_leadstatus": 111,
    "Leads\\kol_lead_kol_territorycode": 113,
    "Leads\\lead_address1_addresstypecode": 107,
    "Leads\\lead_address1_shippingmethodcode": 108,
    "Leads\\lead_address2_addresstypecode": 123,
    "Leads\\lead_address2_shippingmethodcode": 112,
    "Leads\\lead_donotbulkemail": 91,
    "Leads\\lead_donotemail": 94,
    "Leads\\lead_donotfax": 92,
    "Leads\\lead_donotphone": 103,
    "Leads\\lead_donotpostalmail": 90,
    "Leads\\lead_donotsendmm": 104,
    "Leads\\lead_followemail": 97,
    "Leads\\lead_industrycode": 119,
    "Leads\\lead_isautocreate": 95,
    "Leads\\lead_isprivate": 100,
    "Leads\\lead_leadqualitycode": 117,
    "Leads\\lead_leadsourcecode": 118,
    "Leads\\lead_merged": 102,
    "Leads\\lead_participatesinworkflow": 101,
    "Leads\\lead_preferredcontactmethodcode": 116,
    "Leads\\lead_prioritycode": 124,
    "Leads\\lead_salesstage": 114,
    "Leads\\lead_salesstagecode": 120,
    "Leads\\lead_statecode": 127,
    "Leads\\lead_statuscode": 128,
    "Leads\\msdyn_lead_msdyn_gdproptout": 105,
    "Leads\\msdyn_lead_msdyn_salesassignmentresult": 121,
    "Leads\\msdyn_leadgradeoptset": 115,
    "Leads\\msdyn_leadscoretrendoptset": 109,
    "Leads\\need": 126,
    "Leads\\purchaseprocess": 125,
    "Leads\\purchasetimeframe": 122,
    "ListboxSample": 138,
    "Product Details_V": 139,
    "Products": 148,
    "RadioSample": 140,
    "Table1": 141
  },
  "OrderGroupControls": {
    "Group1": {
      "Add_Icon": 11,
      "ALC_lbl": 15,
      "ALC_value": 2,
      "Carton_Quantity_vlaue": 3,
      "CQ_Label": 16,
      "Currency_lbl": 22,
      "Currency_value": 9,
      "Decoded_CB": 5,
      "Decoded_Lbl": 18,
      "Label4_26": 13,
      "Label4_36": 23,
      "Label4_38": 25,
      "Litres_lbl": 27,
      "Litres_Value": 26,
      "Maxprice_lbl": 21,
      "MaxPrice_value": 8,
      "MinPrice_lbl": 20,
      "MinPrice_value": 7,
      "NonRefiil_CB": 6,
      "Non-refill_lbl": 19,
      "Prodcut_lbl": 12,
      "Product _Code": 1,
      "Productcode_lbl": 14,
      "ProductList_CB": 0,
      "Quantity_lbl": 24,
      "Quantity_value": 10,
      "Variant_value": 4,
      "Varient_label": 17
    },
    "Header_1": {
      "Header Label_1": 1,
      "Logo_1": 0
    },
    "YearMonthPicker": {
      "btnSetYearMonth": 4,
      "ddMonth": 3,
      "ddYear": 2,
      "Frame": 1,
      "FrameShadow": 0,
      "lblMonth": 6,
      "lblYear": 5
    }
  },
  "OrderPcfTemplate": {},
  "OrderTemplate": {},
  "OrderXMLTemplate": {
    "attachments": 13,
    "button": 10,
    "checkbox": 12,
    "circle": 14,
    "combobox": 3,
    "datepicker": 4,
    "dropdown": 5,
    "form": 0,
    "gallery": 6,
    "groupContainer": 11,
    "icon": 8,
    "image": 7,
    "label": 1,
    "rectangle": 9,
    "text": 2,
    "timer": 15
  },
  "OverridablePropertiesEntry": {
    "ABV_DataCard1": {},
    "ABV_DataCard2": {},
    "Add_Icon": {},
    "ALC_lbl": {},
    "ALC_value": {},
    "App": {},
    "Attachments_DataCard2": {},
    "Barcode_DataCard1": {},
    "Barcode_DataCard2": {},
    "Bottle_DataCard1": {},
    "Bottle_DataCard2": {},
    "Btl/Ctn_DataCard1": {},
    "Btl/Ctn_DataCard2": {},
    "btnSetYearMonth": {},
    "Button1": {},
    "Button2": {},
    "Button3": {},
    "Button4": {},
    "Carton_Quantity_vlaue": {},
    "Checkbox1": {},
    "Checkbox1_1": {},
    "ComboBox1": {},
    "Contact_DataCard1": {},
    "Contact_DataCard2": {},
    "Container3": {},
    "CQ_Label": {},
    "Create Date_DataCard1": {},
    "Currency_lbl": {},
    "Currency_value": {},
    "CustomCalendar": {},
    "Customer Lead Id_DataCard1": {},
    "Customer Lead Id_DataCard2": {},
    "Customer Lead Id_DataCard3": {},
    "DataCardKey1": {},
    "DataCardKey10": {},
    "DataCardKey11": {},
    "DataCardKey12": {},
    "DataCardKey13": {},
    "DataCardKey14": {},
    "DataCardKey15": {},
    "DataCardKey16": {},
    "DataCardKey17": {},
    "DataCardKey18": {},
    "DataCardKey19": {},
    "DataCardKey2": {},
    "DataCardKey20": {},
    "DataCardKey21": {},
    "DataCardKey22": {},
    "DataCardKey23": {},
    "DataCardKey24": {},
    "DataCardKey25": {},
    "DataCardKey27": {},
    "DataCardKey28": {},
    "DataCardKey29": {},
    "DataCardKey3": {},
    "DataCardKey30": {},
    "DataCardKey31": {},
    "DataCardKey37": {},
    "DataCardKey38": {},
    "DataCardKey4": {},
    "DataCardKey5": {},
    "DataCardKey6": {},
    "DataCardKey7": {},
    "DataCardKey8": {},
    "DataCardKey9": {},
    "DataCardValue1": {},
    "DataCardValue10": {},
    "DataCardValue11": {},
    "DataCardValue12": {},
    "DataCardValue13": {},
    "DataCardValue15": {},
    "DataCardValue16": {},
    "DataCardValue17": {},
    "DataCardValue18": {},
    "DataCardValue19": {},
    "DataCardValue2": {},
    "DataCardValue20": {},
    "DataCardValue21": {},
    "DataCardValue22": {},
    "DataCardValue23": {},
    "DataCardValue25": {},
    "DataCardValue26": {},
    "DataCardValue3": {},
    "DataCardValue32": {},
    "DataCardValue33": {},
    "DataCardValue4": {},
    "DataCardValue5": {},
    "DataCardValue6": {},
    "DataCardValue7": {},
    "DataCardValue8": {},
    "DataCardValue9": {},
    "DateValue1": {},
    "DateValue2": {},
    "DateValue3": {},
    "ddMonth": {},
    "ddYear": {},
    "Decoded_CB": {},
    "Decoded_Lbl": {},
    "Description_DataCard1": {},
    "Description_DataCard2": {},
    "Edit_icon": {},
    "ErrorMessage1": {},
    "ErrorMessage10": {},
    "ErrorMessage11": {},
    "ErrorMessage12": {},
    "ErrorMessage13": {},
    "ErrorMessage14": {},
    "ErrorMessage15": {},
    "ErrorMessage16": {},
    "ErrorMessage17": {},
    "ErrorMessage18": {},
    "ErrorMessage19": {},
    "ErrorMessage2": {},
    "ErrorMessage20": {},
    "ErrorMessage21": {},
    "ErrorMessage22": {},
    "ErrorMessage23": {},
    "ErrorMessage25": {},
    "ErrorMessage26": {},
    "ErrorMessage27": {},
    "ErrorMessage28": {},
    "ErrorMessage3": {},
    "ErrorMessage34": {},
    "ErrorMessage35": {},
    "ErrorMessage4": {},
    "ErrorMessage5": {},
    "ErrorMessage6": {},
    "ErrorMessage7": {},
    "ErrorMessage8": {},
    "ErrorMessage9": {},
    "Expiry Date_DataCard1": {},
    "Expiry Date_DataCard2": {},
    "Expiry Date_DataCard3": {},
    "Form1": {},
    "Form2": {},
    "Form3": {},
    "Form5": {},
    "Frame": {},
    "FrameShadow": {},
    "Gallery1": {},
    "Gallery2": {},
    "Gallery3": {},
    "galleryTemplate1": {},
    "galleryTemplate1_4": {},
    "galleryTemplate2": {},
    "galleryTemplate2_1": {},
    "galleryTemplate3": {},
    "Group1": {},
    "Header Label_1": {},
    "Header Label_2": {},
    "Header_1": {},
    "Home Screen": {},
    "Home_Icon": {},
    "Home_Icon_1": {},
    "HourValue1": {},
    "Icon1": {},
    "Icon2": {},
    "Icon2_1": {},
    "Icon3": {},
    "iconNextMonth": {},
    "iconPrevMonth": {},
    "Image1": {},
    "Image2": {},
    "Image3": {},
    "Image4": {},
    "Image5": {},
    "Item No_DataCard1": {},
    "Item No_DataCard2": {},
    "Label1": {},
    "Label2": {},
    "Label2_1": {},
    "Label2_10": {},
    "Label2_2": {},
    "Label2_3": {},
    "Label2_4": {},
    "Label2_5": {},
    "Label2_6": {},
    "Label2_7": {},
    "Label2_8": {},
    "Label2_9": {},
    "Label3": {},
    "Label4": {},
    "Label4_26": {},
    "Label4_36": {},
    "Label4_38": {},
    "Label5": {},
    "Label6": {},
    "Label7": {},
    "Label8": {},
    "Label9": {},
    "lblMonth": {},
    "LblMonthSelected": {},
    "lblYear": {},
    "Litres_lbl": {},
    "Litres_Value": {},
    "Logo_1": {},
    "Lt/Btl_DataCard1": {},
    "Lt/Btl_DataCard2": {},
    "Max Price (ntz_maxprice)_DataCard1": {},
    "Max Price_DataCard1": {},
    "Maxprice_lbl": {},
    "MaxPrice_value": {},
    "Min Price (ntz_minprice)_DataCard1": {},
    "Min Price_DataCard1": {},
    "MinPrice_lbl": {},
    "MinPrice_value": {},
    "MinuteValue1": {},
    "MinuteValue2": {},
    "ModelDrivenFormIntegration": {
      "Data": {
        "Type": {
          "EnumString": "",
          "Kind": "Table",
          "Name": "Root",
          "Type": [
            {
              "EnumString": "",
              "Kind": "String",
              "Name": "ItemId",
              "Type": []
            },
            {
              "EnumString": "",
              "Kind": "DateTime",
              "Name": "RefreshedOn",
              "Type": []
            }
          ]
        },
        "Version": "1.326"
      }
    },
    "MonthDayGallery": {},
    "Name_DataCard1": {},
    "NextArrow1": {},
    "NonRefiil_CB": {},
    "Non-refill_lbl": {},
    "Prodcut_lbl": {},
    "Product _Code": {},
    "Productcode_lbl": {},
    "ProductList_CB": {},
    "Quantity_DataCard1": {},
    "Quantity_lbl": {},
    "Quantity_value": {},
    "Rectangle1": {},
    "Rectangle1_1": {},
    "Rectangle2": {},
    "Rectangle3": {},
    "Rectangle5": {},
    "SaveButton": {},
    "Screen_AddNewCustomerTargetPricing": {},
    "Screen_ViewCustomerTargetPricing": {},
    "Screen1": {},
    "Separator1": {},
    "Separator2": {},
    "Separator3": {},
    "Separator4": {},
    "SetDefaultTimer": {},
    "StarVisible1": {},
    "StarVisible10": {},
    "StarVisible11": {},
    "StarVisible12": {},
    "StarVisible13": {},
    "StarVisible14": {},
    "StarVisible15": {},
    "StarVisible16": {},
    "StarVisible17": {},
    "StarVisible18": {},
    "StarVisible19": {},
    "StarVisible2": {},
    "StarVisible20": {},
    "StarVisible21": {},
    "StarVisible22": {},
    "StarVisible23": {},
    "StarVisible25": {},
    "StarVisible26": {},
    "StarVisible27": {},
    "StarVisible28": {},
    "StarVisible3": {},
    "StarVisible34": {},
    "StarVisible35": {},
    "StarVisible4": {},
    "StarVisible5": {},
    "StarVisible6": {},
    "StarVisible7": {},
    "StarVisible8": {},
    "StarVisible9": {},
    "Subcircle1_1": {},
    "Subtitle1": {},
    "TextInput1": {},
    "TextInput1_1": {},
    "TextInput1_2": {},
    "TextInput1_3": {},
    "TextInput1_4": {},
    "TextInput1_5": {},
    "TextInput1_6": {},
    "TextInput1_7": {},
    "TextInput12": {},
    "TextInput13": {},
    "TextInput14": {},
    "TextInput15": {},
    "TextInput2": {},
    "TextInput3": {},
    "TextInput4": {},
    "TextInput5": {},
    "TextInput6": {},
    "Title_DataCard1": {},
    "Title1": {},
    "Title1_1": {},
    "Title2_4": {},
    "TodayIcon": {},
    "Variant_DataCard1": {},
    "Variant_value": {},
    "Varient_label": {},
    "WeekdayGallery": {},
    "YearMonthPicker": {}
  },
  "PCFDynamicSchemaForIRRetrievalEntry": {
    "ModelDrivenFormIntegration": {}
  },
  "PublishOrderIndices": {
    "ABV_DataCard1": 145,
    "ABV_DataCard2": 197,
    "Add_Icon": 81,
    "ALC_lbl": 67,
    "ALC_value": 78,
    "App": 0,
    "Attachments_DataCard2": 101,
    "Barcode_DataCard1": 135,
    "Barcode_DataCard2": 202,
    "Bottle_DataCard1": 160,
    "Bottle_DataCard2": 207,
    "Btl/Ctn_DataCard1": 150,
    "Btl/Ctn_DataCard2": 212,
    "btnSetYearMonth": 284,
    "Button1": 180,
    "Button2": 2,
    "Button3": 3,
    "Button4": 106,
    "Carton_Quantity_vlaue": 79,
    "Checkbox1": 46,
    "Checkbox1_1": 48,
    "ComboBox1": 36,
    "Contact_DataCard1": 18,
    "Contact_DataCard2": 248,
    "Container3": 35,
    "CQ_Label": 73,
    "Create Date_DataCard1": 217,
    "Currency_lbl": 60,
    "Currency_value": 66,
    "CustomCalendar": 0,
    "Customer Lead Id_DataCard1": 15,
    "Customer Lead Id_DataCard2": 113,
    "Customer Lead Id_DataCard3": 253,
    "DataCardKey1": 19,
    "DataCardKey10": 214,
    "DataCardKey11": 218,
    "DataCardKey12": 222,
    "DataCardKey13": 230,
    "DataCardKey14": 235,
    "DataCardKey15": 116,
    "DataCardKey16": 128,
    "DataCardKey17": 120,
    "DataCardKey18": 132,
    "DataCardKey19": 152,
    "DataCardKey2": 184,
    "DataCardKey20": 147,
    "DataCardKey21": 137,
    "DataCardKey22": 162,
    "DataCardKey23": 172,
    "DataCardKey24": 157,
    "DataCardKey25": 167,
    "DataCardKey27": 240,
    "DataCardKey28": 245,
    "DataCardKey29": 250,
    "DataCardKey3": 189,
    "DataCardKey30": 255,
    "DataCardKey31": 142,
    "DataCardKey37": 98,
    "DataCardKey38": 103,
    "DataCardKey4": 16,
    "DataCardKey5": 25,
    "DataCardKey6": 194,
    "DataCardKey7": 199,
    "DataCardKey8": 204,
    "DataCardKey9": 209,
    "DataCardValue1": 185,
    "DataCardValue10": 236,
    "DataCardValue11": 241,
    "DataCardValue12": 246,
    "DataCardValue13": 251,
    "DataCardValue15": 122,
    "DataCardValue16": 133,
    "DataCardValue17": 153,
    "DataCardValue18": 148,
    "DataCardValue19": 138,
    "DataCardValue2": 190,
    "DataCardValue20": 163,
    "DataCardValue21": 173,
    "DataCardValue22": 158,
    "DataCardValue23": 168,
    "DataCardValue25": 256,
    "DataCardValue26": 143,
    "DataCardValue3": 195,
    "DataCardValue32": 99,
    "DataCardValue33": 104,
    "DataCardValue4": 200,
    "DataCardValue5": 205,
    "DataCardValue6": 210,
    "DataCardValue7": 215,
    "DataCardValue8": 219,
    "DataCardValue9": 231,
    "DateValue1": 26,
    "DateValue2": 129,
    "DateValue3": 223,
    "ddMonth": 283,
    "ddYear": 282,
    "Decoded_CB": 70,
    "Decoded_Lbl": 68,
    "Description_DataCard1": 187,
    "Description_DataCard2": 118,
    "Edit_icon": 86,
    "ErrorMessage1": 186,
    "ErrorMessage10": 232,
    "ErrorMessage11": 237,
    "ErrorMessage12": 242,
    "ErrorMessage13": 114,
    "ErrorMessage14": 126,
    "ErrorMessage15": 121,
    "ErrorMessage16": 134,
    "ErrorMessage17": 154,
    "ErrorMessage18": 149,
    "ErrorMessage19": 139,
    "ErrorMessage2": 191,
    "ErrorMessage20": 164,
    "ErrorMessage21": 174,
    "ErrorMessage22": 159,
    "ErrorMessage23": 169,
    "ErrorMessage25": 247,
    "ErrorMessage26": 252,
    "ErrorMessage27": 257,
    "ErrorMessage28": 144,
    "ErrorMessage3": 196,
    "ErrorMessage34": 100,
    "ErrorMessage35": 105,
    "ErrorMessage4": 23,
    "ErrorMessage5": 201,
    "ErrorMessage6": 206,
    "ErrorMessage7": 211,
    "ErrorMessage8": 216,
    "ErrorMessage9": 227,
    "Expiry Date_DataCard1": 21,
    "Expiry Date_DataCard2": 123,
    "Expiry Date_DataCard3": 220,
    "Form1": 14,
    "Form2": 112,
    "Form3": 181,
    "Form5": 95,
    "Frame": 274,
    "FrameShadow": 279,
    "Gallery1": 84,
    "Gallery2": 175,
    "Gallery3": 258,
    "galleryTemplate1": 85,
    "galleryTemplate1_4": 272,
    "galleryTemplate2": 176,
    "galleryTemplate2_1": 276,
    "galleryTemplate3": 259,
    "Group1": 28,
    "Header Label_1": 10,
    "Header Label_2": 108,
    "Header_1": 11,
    "Home Screen": 3,
    "Home_Icon": 9,
    "Home_Icon_1": 110,
    "HourValue1": 224,
    "Icon1": 58,
    "Icon2": 178,
    "Icon2_1": 179,
    "Icon3": 87,
    "iconNextMonth": 268,
    "iconPrevMonth": 267,
    "Image1": 0,
    "Image2": 1,
    "Image3": 5,
    "Image4": 260,
    "Image5": 109,
    "Item No_DataCard1": 130,
    "Item No_DataCard2": 192,
    "Label1": 4,
    "Label2": 37,
    "Label2_1": 39,
    "Label2_10": 56,
    "Label2_2": 41,
    "Label2_3": 43,
    "Label2_4": 45,
    "Label2_5": 47,
    "Label2_6": 49,
    "Label2_7": 51,
    "Label2_8": 53,
    "Label2_9": 55,
    "Label3": 83,
    "Label4": 33,
    "Label4_26": 30,
    "Label4_36": 32,
    "Label4_38": 29,
    "Label5": 177,
    "Label6": 111,
    "Label7": 27,
    "Label8": 13,
    "Label9": 82,
    "lblMonth": 281,
    "LblMonthSelected": 266,
    "lblYear": 280,
    "Litres_lbl": 69,
    "Litres_Value": 77,
    "Logo_1": 12,
    "Lt/Btl_DataCard1": 170,
    "Lt/Btl_DataCard2": 228,
    "Max Price (ntz_maxprice)_DataCard1": 233,
    "Max Price_DataCard1": 155,
    "Maxprice_lbl": 34,
    "MaxPrice_value": 65,
    "Min Price (ntz_minprice)_DataCard1": 238,
    "Min Price_DataCard1": 165,
    "MinPrice_lbl": 59,
    "MinPrice_value": 64,
    "MinuteValue1": 125,
    "MinuteValue2": 226,
    "ModelDrivenFormIntegration": 2,
    "MonthDayGallery": 275,
    "Name_DataCard1": 182,
    "NextArrow1": 262,
    "NonRefiil_CB": 75,
    "Non-refill_lbl": 71,
    "Prodcut_lbl": 31,
    "Product _Code": 76,
    "Productcode_lbl": 72,
    "ProductList_CB": 63,
    "Quantity_DataCard1": 140,
    "Quantity_lbl": 61,
    "Quantity_value": 62,
    "Rectangle1": 6,
    "Rectangle1_1": 265,
    "Rectangle2": 8,
    "Rectangle3": 107,
    "Rectangle5": 7,
    "SaveButton": 94,
    "Screen_AddNewCustomerTargetPricing": 95,
    "Screen_ViewCustomerTargetPricing": 198,
    "Screen1": 10,
    "Separator1": 22,
    "Separator2": 124,
    "Separator3": 225,
    "Separator4": 264,
    "SetDefaultTimer": 285,
    "StarVisible1": 183,
    "StarVisible10": 229,
    "StarVisible11": 234,
    "StarVisible12": 239,
    "StarVisible13": 115,
    "StarVisible14": 127,
    "StarVisible15": 119,
    "StarVisible16": 131,
    "StarVisible17": 151,
    "StarVisible18": 146,
    "StarVisible19": 136,
    "StarVisible2": 188,
    "StarVisible20": 161,
    "StarVisible21": 171,
    "StarVisible22": 156,
    "StarVisible23": 166,
    "StarVisible25": 244,
    "StarVisible26": 249,
    "StarVisible27": 254,
    "StarVisible28": 141,
    "StarVisible3": 193,
    "StarVisible34": 97,
    "StarVisible35": 102,
    "StarVisible4": 24,
    "StarVisible5": 198,
    "StarVisible6": 203,
    "StarVisible7": 208,
    "StarVisible8": 213,
    "StarVisible9": 221,
    "Subcircle1_1": 278,
    "Subtitle1": 263,
    "TextInput1": 38,
    "TextInput1_1": 40,
    "TextInput1_2": 42,
    "TextInput1_3": 44,
    "TextInput1_4": 50,
    "TextInput1_5": 52,
    "TextInput1_6": 54,
    "TextInput1_7": 57,
    "TextInput12": 90,
    "TextInput13": 91,
    "TextInput14": 93,
    "TextInput15": 92,
    "TextInput2": 88,
    "TextInput3": 17,
    "TextInput4": 20,
    "TextInput5": 89,
    "TextInput6": 117,
    "Title_DataCard1": 96,
    "Title1": 261,
    "Title1_1": 273,
    "Title2_4": 277,
    "TodayIcon": 269,
    "Variant_DataCard1": 243,
    "Variant_value": 80,
    "Varient_label": 74,
    "WeekdayGallery": 271,
    "YearMonthPicker": 270
  },
  "ResourcesJsonIndices": {
    "Image-Bacardi-hpb": 1,
    "Image-Craft-Beer": 2,
    "Image-decorative-green-color-modern-geometric-stripes-transparent-background-vector_1055-12665 (1)": 3,
    "Image-download": 4,
    "Image-Kollaras_and_Co": 5,
    "Image-Mogul-Banner": 6,
    "Image-OIP": 8,
    "Image-OIP (5)": 7,
    "Image-Peroni": 9,
    "Image-PowerAddictWaterMark": 11,
    "Image-PowerAddictWaterMark1": 10,
    "Image-SampleImage": 0
  },
  "RuleScreenIdWithoutScreen": {},
  "TemplateVersions": {},
  "VolatileProperties": {
    "AnalysisLoadTime": 3.4695115,
    "ControlCount": {
      "839baf53ea1543f795c43431334252fa": 1,
      "attachments": 1,
      "button": 6,
      "checkbox": 4,
      "circle": 1,
      "combobox": 8,
      "datepicker": 3,
      "dropdown": 5,
      "form": 4,
      "gallery": 5,
      "galleryTemplate": 5,
      "group": 3,
      "groupContainer": 1,
      "hostControl": 1,
      "icon": 12,
      "image": 6,
      "label": 137,
      "rectangle": 8,
      "screen": 4,
      "text": 44,
      "timer": 1,
      "typedDataCard": 32
    },
    "DeserializationLoadTime": 6.3941286,
    "ErrorCount": 42
  },
  "WasLocalDatabaseReferencesEmpty": false
}