{
  "ComponentIndexes": {},
  "ControlUniqueGuids": {},
  "ControlUniqueIds": {
    "ABV_DataCard1": 230,
    "ABV_DataCard2": 28,
    "Add_Icon": 155,
    "ALC_lbl": 151,
    "ALC_value": 159,
    "App": 1,
    "Attachments_DataCard2": 184,
    "Barcode_DataCard1": 220,
    "Barcode_DataCard2": 33,
    "Bottle_DataCard1": 245,
    "Bottle_DataCard2": 38,
    "Btl/Ctn_DataCard1": 235,
    "Btl/Ctn_DataCard2": 43,
    "Button1": 265,
    "Button2": 7,
    "Button3": 8,
    "Button4": 189,
    "Carton_Quantity_vlaue": 156,
    "Checkbox1": 118,
    "Checkbox1_1": 120,
    "Checkbox2": 163,
    "Checkbox2_1": 164,
    "ComboBox1": 108,
    "Contact_DataCard1": 98,
    "Contact_DataCard2": 79,
    "Container3": 107,
    "CQ_Label": 152,
    "Create Date_DataCard1": 48,
    "Currency_lbl": 143,
    "Currency_value": 144,
    "Customer Lead Id_DataCard1": 95,
    "Customer Lead Id_DataCard2": 198,
    "Customer Lead Id_DataCard3": 84,
    "DataCardKey1": 99,
    "DataCardKey10": 45,
    "DataCardKey11": 49,
    "DataCardKey12": 53,
    "DataCardKey13": 61,
    "DataCardKey14": 66,
    "DataCardKey15": 200,
    "DataCardKey16": 213,
    "DataCardKey17": 205,
    "DataCardKey18": 217,
    "DataCardKey19": 237,
    "DataCardKey2": 15,
    "DataCardKey20": 232,
    "DataCardKey21": 222,
    "DataCardKey22": 247,
    "DataCardKey23": 257,
    "DataCardKey24": 242,
    "DataCardKey25": 252,
    "DataCardKey27": 71,
    "DataCardKey28": 76,
    "DataCardKey29": 81,
    "DataCardKey3": 20,
    "DataCardKey30": 86,
    "DataCardKey31": 227,
    "DataCardKey37": 181,
    "DataCardKey38": 186,
    "DataCardKey4": 96,
    "DataCardKey5": 105,
    "DataCardKey6": 25,
    "DataCardKey7": 30,
    "DataCardKey8": 35,
    "DataCardKey9": 40,
    "DataCardValue1": 16,
    "DataCardValue10": 67,
    "DataCardValue11": 72,
    "DataCardValue12": 77,
    "DataCardValue13": 82,
    "DataCardValue14": 201,
    "DataCardValue15": 207,
    "DataCardValue16": 218,
    "DataCardValue17": 238,
    "DataCardValue18": 233,
    "DataCardValue19": 223,
    "DataCardValue2": 21,
    "DataCardValue20": 248,
    "DataCardValue21": 258,
    "DataCardValue22": 243,
    "DataCardValue23": 253,
    "DataCardValue25": 87,
    "DataCardValue26": 228,
    "DataCardValue3": 26,
    "DataCardValue32": 182,
    "DataCardValue33": 187,
    "DataCardValue4": 31,
    "DataCardValue5": 36,
    "DataCardValue6": 41,
    "DataCardValue7": 46,
    "DataCardValue8": 50,
    "DataCardValue9": 62,
    "DateValue1": 106,
    "DateValue2": 214,
    "DateValue3": 54,
    "Decoded_CB": 139,
    "Decoded_Lbl": 136,
    "Description_DataCard1": 18,
    "Description_DataCard2": 203,
    "Edit_icon": 175,
    "ErrorMessage1": 17,
    "ErrorMessage10": 63,
    "ErrorMessage11": 68,
    "ErrorMessage12": 73,
    "ErrorMessage13": 202,
    "ErrorMessage14": 211,
    "ErrorMessage15": 206,
    "ErrorMessage16": 219,
    "ErrorMessage17": 239,
    "ErrorMessage18": 234,
    "ErrorMessage19": 224,
    "ErrorMessage2": 22,
    "ErrorMessage20": 249,
    "ErrorMessage21": 259,
    "ErrorMessage22": 244,
    "ErrorMessage23": 254,
    "ErrorMessage25": 78,
    "ErrorMessage26": 83,
    "ErrorMessage27": 88,
    "ErrorMessage28": 229,
    "ErrorMessage3": 27,
    "ErrorMessage34": 183,
    "ErrorMessage35": 188,
    "ErrorMessage4": 103,
    "ErrorMessage5": 32,
    "ErrorMessage6": 37,
    "ErrorMessage7": 42,
    "ErrorMessage8": 47,
    "ErrorMessage9": 58,
    "Expiry Date_DataCard1": 101,
    "Expiry Date_DataCard2": 208,
    "Expiry Date_DataCard3": 51,
    "Form1": 94,
    "Form2": 197,
    "Form3": 12,
    "Form5": 178,
    "Gallery1": 161,
    "Gallery2": 260,
    "galleryTemplate1": 162,
    "galleryTemplate2": 261,
    "Group1": 191,
    "Header Label_1": 90,
    "Header Label_2": 193,
    "Header_1": 190,
    "Home Screen": 4,
    "Home_Icon": 92,
    "Home_Icon_1": 195,
    "HourValue1": 55,
    "Icon1": 130,
    "Icon2": 263,
    "Icon2_1": 264,
    "Icon3": 176,
    "Image1": 5,
    "Image2": 6,
    "Image3": 10,
    "Image5": 194,
    "Item No_DataCard1": 215,
    "Item No_DataCard2": 23,
    "Label1": 9,
    "Label2": 109,
    "Label2_1": 111,
    "Label2_10": 128,
    "Label2_2": 113,
    "Label2_3": 115,
    "Label2_4": 117,
    "Label2_5": 119,
    "Label2_6": 121,
    "Label2_7": 123,
    "Label2_8": 125,
    "Label2_9": 127,
    "Label3": 160,
    "Label4": 134,
    "Label4_26": 131,
    "Label4_36": 132,
    "Label4_38": 133,
    "Label5": 262,
    "Label6": 196,
    "Label8": 93,
    "Litres_lbl": 153,
    "Litres_Value": 158,
    "Logo_1": 91,
    "Lt/Btl_DataCard1": 255,
    "Lt/Btl_DataCard2": 59,
    "Max Price (ntz_maxprice)_DataCard1": 64,
    "Max Price_DataCard1": 240,
    "Maxprice_lbl": 138,
    "MaxPrice_value": 148,
    "Min Price (ntz_minprice)_DataCard1": 69,
    "Min Price_DataCard1": 250,
    "MinPrice_lbl": 141,
    "MinPrice_value": 147,
    "MinuteValue1": 210,
    "MinuteValue2": 57,
    "ModelDrivenFormIntegration": 3,
    "Name_DataCard1": 13,
    "NonRefiil_CB": 140,
    "Non-refill_lbl": 135,
    "Prodcut_lbl": 137,
    "Product _Code": 157,
    "Productcode_lbl": 150,
    "ProductList_CB": 146,
    "Quantity_DataCard1": 225,
    "Quantity_lbl": 142,
    "Quantity_value": 145,
    "SaveButton": 177,
    "Screen_AddNewCustomerTargetPricing": 89,
    "Screen_ViewCustomerTargetPricing": 192,
    "Screen1": 11,
    "Separator1": 102,
    "Separator2": 209,
    "Separator3": 56,
    "StarVisible1": 14,
    "StarVisible10": 60,
    "StarVisible11": 65,
    "StarVisible12": 70,
    "StarVisible13": 199,
    "StarVisible14": 212,
    "StarVisible15": 204,
    "StarVisible16": 216,
    "StarVisible17": 236,
    "StarVisible18": 231,
    "StarVisible19": 221,
    "StarVisible2": 19,
    "StarVisible20": 246,
    "StarVisible21": 256,
    "StarVisible22": 241,
    "StarVisible23": 251,
    "StarVisible25": 75,
    "StarVisible26": 80,
    "StarVisible27": 85,
    "StarVisible28": 226,
    "StarVisible3": 24,
    "StarVisible34": 180,
    "StarVisible35": 185,
    "StarVisible4": 104,
    "StarVisible5": 29,
    "StarVisible6": 34,
    "StarVisible7": 39,
    "StarVisible8": 44,
    "StarVisible9": 52,
    "TextInput1": 110,
    "TextInput1_1": 112,
    "TextInput1_2": 114,
    "TextInput1_3": 116,
    "TextInput1_4": 122,
    "TextInput1_5": 124,
    "TextInput1_6": 126,
    "TextInput1_7": 129,
    "TextInput12": 171,
    "TextInput12_1": 170,
    "TextInput13": 172,
    "TextInput14": 173,
    "TextInput15": 174,
    "TextInput2": 165,
    "TextInput3": 97,
    "TextInput4": 100,
    "TextInput5": 166,
    "TextInput6": 167,
    "TextInput7": 168,
    "TextInput8": 169,
    "Title_DataCard1": 179,
    "Variant_DataCard1": 74,
    "Variant_value": 154,
    "Varient_label": 149
  },
  "FunctionParamsInvariantScripts": {},
  "FunctionParamsInvariantScriptsOnInstances": {},
  "HeaderLastSavedDateTimeUTC": "01/02/2023 13:39:35",
  "IsLegacyComponentAllowGlobalScopeCase": false,
  "LocalConnectionIDReferences": {
    "592d4f51-6b18-4e5e-95a9-c6bfed89113c": "\"/providers/microsoft.powerapps/apis/shared_excelonlinebusiness/connections/shared-excelonlinebu-0ee4e134-c547-4b27-a12b-bdcc348f4d25\"",
    "da5913c3-4335-450f-8ab9-c25ed7aa33e3": "\"/providers/microsoft.powerapps/apis/shared_logicflows/connections/7dae44c6192b48c4ae31043b2a88d0fe-c8c59f0b20851dda\"",
    "df4281c0-e0a4-49f7-9d94-20b3d42bd4f3": "\"/providers/microsoft.powerapps/apis/shared_sql/connections/e53bf8da15304ddf9d52466baa8ce6e1\"",
    "f3d9070f-381e-4a91-916f-c9ad3af0d19a": "\"/providers/microsoft.powerapps/apis/shared_sharepointonline/connections/21dc9c9140e64c68b0f82cc61a5c48c1\""
  },
  "LocalDatabaseReferencesAsEmpty": false,
  "LocalResourceFileNames": {
    "Bacardi-hpb": "0001.jpg",
    "Craft-Beer": "0002.jpg",
    "decorative-green-color-modern-geometric-stripes-transparent-background-vector_1055-12665 (1)": "0003.jpg",
    "download": "0004.png",
    "Kollaras_and_Co": "0005.png",
    "Mogul-Banner": "0006.jpg",
    "OIP": "0008.jpeg",
    "OIP (5)": "0007.jpeg",
    "Peroni": "0009.jpg"
  },
  "LocalResourceRootPaths": {
    "Bacardi-hpb": "https://docserverpwaprodseau.blob.core.windows.net/6657787c-2320-40cd-9e68-7c0eca6074df-1/resource/Assets0Images00001.jpg?sv=2017-04-17&sr=b&sig=6eSeRqbJxSJp7OEp593cceIWfo24YossEJxziFW59Eg%3D&spr=https&se=2023-01-03T13%3A06%3A46Z&sp=r",
    "Craft-Beer": "https://docserverpwaprodseau.blob.core.windows.net/6657787c-2320-40cd-9e68-7c0eca6074df-1/resource/Assets0Images00002.jpg?sv=2017-04-17&sr=b&sig=8RPsEDyLsL7t1RcRsENpjzUUKeYBZheQXiOeiPvJU44%3D&spr=https&se=2023-01-03T13%3A06%3A46Z&sp=r",
    "decorative-green-color-modern-geometric-stripes-transparent-background-vector_1055-12665 (1)": "https://docserverpwaprodseau.blob.core.windows.net/6657787c-2320-40cd-9e68-7c0eca6074df-1/resource/Assets0Images00003.jpg?sv=2017-04-17&sr=b&sig=309zebihb1p025LRx%2BRUddURSmJ%2Bnl6sjBzc%2FSqH8yg%3D&spr=https&se=2023-01-03T13%3A06%3A46Z&sp=r",
    "download": "https://docserverpwaprodseau.blob.core.windows.net/6657787c-2320-40cd-9e68-7c0eca6074df-1/resource/Assets0Images00004.png?sv=2017-04-17&sr=b&sig=sk6JWlvB6GxiUxORSFsbSfY%2F8zHEP5T7%2B2mm0WQLmMY%3D&spr=https&se=2023-01-03T13%3A06%3A46Z&sp=r",
    "Kollaras_and_Co": "https://docserverpwaprodseau.blob.core.windows.net/6657787c-2320-40cd-9e68-7c0eca6074df-1/resource/Assets0Images00005.png?sv=2017-04-17&sr=b&sig=ikM%2FH42FUv1S9P2SIX9OjZ7rqee%2FI5emoNp7aHGZ7qU%3D&spr=https&se=2023-01-03T13%3A06%3A46Z&sp=r",
    "Mogul-Banner": "https://docserverpwaprodseau.blob.core.windows.net/6657787c-2320-40cd-9e68-7c0eca6074df-1/resource/Assets0Images00006.jpg?sv=2017-04-17&sr=b&sig=zBZFBIsdpgpVkp7VMjFl%2BqZfw4jQtIMcCnRDC0wo5ZU%3D&spr=https&se=2023-01-03T13%3A06%3A46Z&sp=r",
    "OIP": "https://docserverpwaprodseau.blob.core.windows.net/6657787c-2320-40cd-9e68-7c0eca6074df-1/resource/Assets0Images00008.jpeg?sv=2017-04-17&sr=b&sig=CA8hpQsVqbIXlW9G6OojvRsz%2BveX5vJ3Ri%2FKwsXG9pQ%3D&spr=https&se=2023-01-03T13%3A06%3A46Z&sp=r",
    "OIP (5)": "https://docserverpwaprodseau.blob.core.windows.net/6657787c-2320-40cd-9e68-7c0eca6074df-1/resource/Assets0Images00007.jpeg?sv=2017-04-17&sr=b&sig=jCz5G7KpW5rhwBEGLpi7RcAPQ1Ma6vgrb2UYXvQgevk%3D&spr=https&se=2023-01-03T13%3A06%3A46Z&sp=r",
    "Peroni": "https://docserverpwaprodseau.blob.core.windows.net/6657787c-2320-40cd-9e68-7c0eca6074df-1/resource/Assets0Images00009.jpg?sv=2017-04-17&sr=b&sig=gtLstWjLJ4IK5W9dcOMR1g6Bswij8QA1TkaYnHxR80s%3D&spr=https&se=2023-01-03T13%3A06%3A46Z&sp=r"
  },
  "OrderComponentMetadata": {},
  "OrderComponentTemplate": {},
  "OrderDataSource": {
    "Accounts": 142,
    "Accounts\\account_accountcategorycode": 19,
    "Accounts\\account_accountclassificationcode": 22,
    "Accounts\\account_accountratingcode": 32,
    "Accounts\\account_address1_addresstypecode": 17,
    "Accounts\\account_address1_freighttermscode": 20,
    "Accounts\\account_address1_shippingmethodcode": 18,
    "Accounts\\account_address2_addresstypecode": 33,
    "Accounts\\account_address2_freighttermscode": 25,
    "Accounts\\account_address2_shippingmethodcode": 35,
    "Accounts\\account_businesstypecode": 29,
    "Accounts\\account_creditonhold": 2,
    "Accounts\\account_customersizecode": 23,
    "Accounts\\account_customertypecode": 34,
    "Accounts\\account_donotbulkemail": 5,
    "Accounts\\account_donotbulkpostalmail": 3,
    "Accounts\\account_donotemail": 7,
    "Accounts\\account_donotfax": 6,
    "Accounts\\account_donotphone": 13,
    "Accounts\\account_donotpostalmail": 1,
    "Accounts\\account_donotsendmm": 14,
    "Accounts\\account_followemail": 8,
    "Accounts\\account_industrycode": 28,
    "Accounts\\account_isprivate": 11,
    "Accounts\\account_marketingonly": 10,
    "Accounts\\account_merged": 12,
    "Accounts\\account_ownershipcode": 24,
    "Accounts\\account_participatesinworkflow": 9,
    "Accounts\\account_paymenttermscode": 31,
    "Accounts\\account_preferredappointmentdaycode": 36,
    "Accounts\\account_preferredappointmenttimecode": 21,
    "Accounts\\account_preferredcontactmethodcode": 27,
    "Accounts\\account_shippingmethodcode": 30,
    "Accounts\\account_statecode": 39,
    "Accounts\\account_statuscode": 40,
    "Accounts\\account_territorycode": 37,
    "Accounts\\cdi_account_cdi_allowtextmessages": 4,
    "Accounts\\default.cds_account_views": 129,
    "Accounts\\kol_account_kol_blocked": 15,
    "Accounts\\kol_responsibilitycentre": 26,
    "Accounts\\kol_segmentoptions": 38,
    "Accounts\\msdyn_account_msdyn_gdproptout": 16,
    "ComboBoxSample": 134,
    "Contacts": 143,
    "Contacts\\cdi_contact_cdi_allowtextmessages": 44,
    "Contacts\\contact_accountrolecode": 60,
    "Contacts\\contact_address1_addresstypecode": 81,
    "Contacts\\contact_address1_freighttermscode": 64,
    "Contacts\\contact_address1_shippingmethodcode": 58,
    "Contacts\\contact_address2_addresstypecode": 73,
    "Contacts\\contact_address2_freighttermscode": 69,
    "Contacts\\contact_address2_shippingmethodcode": 62,
    "Contacts\\contact_address3_addresstypecode": 79,
    "Contacts\\contact_address3_freighttermscode": 67,
    "Contacts\\contact_address3_shippingmethodcode": 76,
    "Contacts\\contact_creditonhold": 53,
    "Contacts\\contact_customersizecode": 77,
    "Contacts\\contact_customertypecode": 74,
    "Contacts\\contact_donotbulkemail": 50,
    "Contacts\\contact_donotbulkpostalmail": 55,
    "Contacts\\contact_donotemail": 46,
    "Contacts\\contact_donotfax": 43,
    "Contacts\\contact_donotphone": 52,
    "Contacts\\contact_donotpostalmail": 48,
    "Contacts\\contact_donotsendmm": 51,
    "Contacts\\contact_educationcode": 75,
    "Contacts\\contact_familystatuscode": 59,
    "Contacts\\contact_followemail": 42,
    "Contacts\\contact_gendercode": 72,
    "Contacts\\contact_haschildrencode": 71,
    "Contacts\\contact_isautocreate": 47,
    "Contacts\\contact_isbackofficecustomer": 45,
    "Contacts\\contact_isprivate": 49,
    "Contacts\\contact_leadsourcecode": 70,
    "Contacts\\contact_marketingonly": 54,
    "Contacts\\contact_merged": 41,
    "Contacts\\contact_msdyn_orgchangestatus": 63,
    "Contacts\\contact_participatesinworkflow": 56,
    "Contacts\\contact_paymenttermscode": 78,
    "Contacts\\contact_preferredappointmentdaycode": 80,
    "Contacts\\contact_preferredappointmenttimecode": 61,
    "Contacts\\contact_preferredcontactmethodcode": 66,
    "Contacts\\contact_shippingmethodcode": 65,
    "Contacts\\contact_statecode": 82,
    "Contacts\\contact_statuscode": 83,
    "Contacts\\contact_territorycode": 68,
    "Contacts\\default.cds_contact_views": 130,
    "Contacts\\msdyn_contact_msdyn_gdproptout": 57,
    "Currencies": 144,
    "Currencies\\default.cds_transactioncurrency_views": 131,
    "Currencies\\transactioncurrency_statecode": 84,
    "Currencies\\transactioncurrency_statuscode": 85,
    "Customer Target Pricing": 145,
    "Customer Target Pricing Deploy List": 135,
    "Customer Target Pricing\\default.cds_ntz_customertargetpricing_views": 132,
    "Customer Target Pricing\\ntz_customertargetpricing_ntz_decoded": 87,
    "Customer Target Pricing\\ntz_customertargetpricing_ntz_nonrefill": 86,
    "Customer Target Pricing\\ntz_customertargetpricing_statecode": 88,
    "Customer Target Pricing\\ntz_customertargetpricing_statuscode": 89,
    "CustomGallerySample": 136,
    "DropDownSample": 137,
    "flowExcelData": 147,
    "GetExcelData": 0,
    "Leads": 146,
    "Leads\\budgetstatus": 106,
    "Leads\\cdi_lead_cdi_allowtextmessages": 92,
    "Leads\\confirminterest": 91,
    "Leads\\decisionmaker": 100,
    "Leads\\default.cds_lead_views": 133,
    "Leads\\evaluatefit": 95,
    "Leads\\initialcommunication": 110,
    "Leads\\kol_lead_kol_leadstatus": 111,
    "Leads\\kol_lead_kol_territorycode": 113,
    "Leads\\lead_address1_addresstypecode": 107,
    "Leads\\lead_address1_shippingmethodcode": 108,
    "Leads\\lead_address2_addresstypecode": 123,
    "Leads\\lead_address2_shippingmethodcode": 112,
    "Leads\\lead_donotbulkemail": 93,
    "Leads\\lead_donotemail": 97,
    "Leads\\lead_donotfax": 94,
    "Leads\\lead_donotphone": 103,
    "Leads\\lead_donotpostalmail": 90,
    "Leads\\lead_donotsendmm": 104,
    "Leads\\lead_followemail": 98,
    "Leads\\lead_industrycode": 119,
    "Leads\\lead_isautocreate": 96,
    "Leads\\lead_isprivate": 101,
    "Leads\\lead_leadqualitycode": 117,
    "Leads\\lead_leadsourcecode": 118,
    "Leads\\lead_merged": 102,
    "Leads\\lead_participatesinworkflow": 99,
    "Leads\\lead_preferredcontactmethodcode": 116,
    "Leads\\lead_prioritycode": 124,
    "Leads\\lead_salesstage": 114,
    "Leads\\lead_salesstagecode": 120,
    "Leads\\lead_statecode": 127,
    "Leads\\lead_statuscode": 128,
    "Leads\\msdyn_lead_msdyn_gdproptout": 105,
    "Leads\\msdyn_lead_msdyn_salesassignmentresult": 121,
    "Leads\\msdyn_leadgradeoptset": 115,
    "Leads\\msdyn_leadscoretrendoptset": 109,
    "Leads\\need": 126,
    "Leads\\purchaseprocess": 125,
    "Leads\\purchasetimeframe": 122,
    "ListboxSample": 138,
    "Product Details_V": 139,
    "Products": 148,
    "RadioSample": 140,
    "Table1": 141
  },
  "OrderGroupControls": {
    "Group1": {
      "Add_Icon": 11,
      "ALC_lbl": 15,
      "ALC_value": 2,
      "Carton_Quantity_vlaue": 3,
      "CQ_Label": 16,
      "Currency_lbl": 22,
      "Currency_value": 9,
      "Decoded_CB": 5,
      "Decoded_Lbl": 18,
      "Label4_26": 13,
      "Label4_36": 23,
      "Label4_38": 25,
      "Litres_lbl": 27,
      "Litres_Value": 26,
      "Maxprice_lbl": 21,
      "MaxPrice_value": 8,
      "MinPrice_lbl": 20,
      "MinPrice_value": 7,
      "NonRefiil_CB": 6,
      "Non-refill_lbl": 19,
      "Prodcut_lbl": 12,
      "Product _Code": 1,
      "Productcode_lbl": 14,
      "ProductList_CB": 0,
      "Quantity_lbl": 24,
      "Quantity_value": 10,
      "Variant_value": 4,
      "Varient_label": 17
    },
    "Header_1": {
      "Header Label_1": 1,
      "Logo_1": 0
    }
  },
  "OrderPcfTemplate": {},
  "OrderTemplate": {},
  "OrderXMLTemplate": {
    "attachments": 12,
    "button": 1,
    "checkbox": 10,
    "combobox": 5,
    "datepicker": 6,
    "dropdown": 7,
    "form": 3,
    "gallery": 11,
    "groupContainer": 9,
    "icon": 8,
    "image": 0,
    "label": 2,
    "text": 4
  },
  "OverridablePropertiesEntry": {
    "ABV_DataCard1": {},
    "ABV_DataCard2": {},
    "Add_Icon": {},
    "ALC_lbl": {},
    "ALC_value": {},
    "App": {},
    "Attachments_DataCard2": {},
    "Barcode_DataCard1": {},
    "Barcode_DataCard2": {},
    "Bottle_DataCard1": {},
    "Bottle_DataCard2": {},
    "Btl/Ctn_DataCard1": {},
    "Btl/Ctn_DataCard2": {},
    "Button1": {},
    "Button2": {},
    "Button3": {},
    "Button4": {},
    "Carton_Quantity_vlaue": {},
    "Checkbox1": {},
    "Checkbox1_1": {},
    "Checkbox2": {},
    "Checkbox2_1": {},
    "ComboBox1": {},
    "Contact_DataCard1": {},
    "Contact_DataCard2": {},
    "Container3": {},
    "CQ_Label": {},
    "Create Date_DataCard1": {},
    "Currency_lbl": {},
    "Currency_value": {},
    "Customer Lead Id_DataCard1": {},
    "Customer Lead Id_DataCard2": {},
    "Customer Lead Id_DataCard3": {},
    "DataCardKey1": {},
    "DataCardKey10": {},
    "DataCardKey11": {},
    "DataCardKey12": {},
    "DataCardKey13": {},
    "DataCardKey14": {},
    "DataCardKey15": {},
    "DataCardKey16": {},
    "DataCardKey17": {},
    "DataCardKey18": {},
    "DataCardKey19": {},
    "DataCardKey2": {},
    "DataCardKey20": {},
    "DataCardKey21": {},
    "DataCardKey22": {},
    "DataCardKey23": {},
    "DataCardKey24": {},
    "DataCardKey25": {},
    "DataCardKey27": {},
    "DataCardKey28": {},
    "DataCardKey29": {},
    "DataCardKey3": {},
    "DataCardKey30": {},
    "DataCardKey31": {},
    "DataCardKey37": {},
    "DataCardKey38": {},
    "DataCardKey4": {},
    "DataCardKey5": {},
    "DataCardKey6": {},
    "DataCardKey7": {},
    "DataCardKey8": {},
    "DataCardKey9": {},
    "DataCardValue1": {},
    "DataCardValue10": {},
    "DataCardValue11": {},
    "DataCardValue12": {},
    "DataCardValue13": {},
    "DataCardValue14": {},
    "DataCardValue15": {},
    "DataCardValue16": {},
    "DataCardValue17": {},
    "DataCardValue18": {},
    "DataCardValue19": {},
    "DataCardValue2": {},
    "DataCardValue20": {},
    "DataCardValue21": {},
    "DataCardValue22": {},
    "DataCardValue23": {},
    "DataCardValue25": {},
    "DataCardValue26": {},
    "DataCardValue3": {},
    "DataCardValue32": {},
    "DataCardValue33": {},
    "DataCardValue4": {},
    "DataCardValue5": {},
    "DataCardValue6": {},
    "DataCardValue7": {},
    "DataCardValue8": {},
    "DataCardValue9": {},
    "DateValue1": {},
    "DateValue2": {},
    "DateValue3": {},
    "Decoded_CB": {},
    "Decoded_Lbl": {},
    "Description_DataCard1": {},
    "Description_DataCard2": {},
    "Edit_icon": {},
    "ErrorMessage1": {},
    "ErrorMessage10": {},
    "ErrorMessage11": {},
    "ErrorMessage12": {},
    "ErrorMessage13": {},
    "ErrorMessage14": {},
    "ErrorMessage15": {},
    "ErrorMessage16": {},
    "ErrorMessage17": {},
    "ErrorMessage18": {},
    "ErrorMessage19": {},
    "ErrorMessage2": {},
    "ErrorMessage20": {},
    "ErrorMessage21": {},
    "ErrorMessage22": {},
    "ErrorMessage23": {},
    "ErrorMessage25": {},
    "ErrorMessage26": {},
    "ErrorMessage27": {},
    "ErrorMessage28": {},
    "ErrorMessage3": {},
    "ErrorMessage34": {},
    "ErrorMessage35": {},
    "ErrorMessage4": {},
    "ErrorMessage5": {},
    "ErrorMessage6": {},
    "ErrorMessage7": {},
    "ErrorMessage8": {},
    "ErrorMessage9": {},
    "Expiry Date_DataCard1": {},
    "Expiry Date_DataCard2": {},
    "Expiry Date_DataCard3": {},
    "Form1": {},
    "Form2": {},
    "Form3": {},
    "Form5": {},
    "Gallery1": {},
    "Gallery2": {},
    "galleryTemplate1": {},
    "galleryTemplate2": {},
    "Group1": {},
    "Header Label_1": {},
    "Header Label_2": {},
    "Header_1": {},
    "Home Screen": {},
    "Home_Icon": {},
    "Home_Icon_1": {},
    "HourValue1": {},
    "Icon1": {},
    "Icon2": {},
    "Icon2_1": {},
    "Icon3": {},
    "Image1": {},
    "Image2": {},
    "Image3": {},
    "Image5": {},
    "Item No_DataCard1": {},
    "Item No_DataCard2": {},
    "Label1": {},
    "Label2": {},
    "Label2_1": {},
    "Label2_10": {},
    "Label2_2": {},
    "Label2_3": {},
    "Label2_4": {},
    "Label2_5": {},
    "Label2_6": {},
    "Label2_7": {},
    "Label2_8": {},
    "Label2_9": {},
    "Label3": {},
    "Label4": {},
    "Label4_26": {},
    "Label4_36": {},
    "Label4_38": {},
    "Label5": {},
    "Label6": {},
    "Label8": {},
    "Litres_lbl": {},
    "Litres_Value": {},
    "Logo_1": {},
    "Lt/Btl_DataCard1": {},
    "Lt/Btl_DataCard2": {},
    "Max Price (ntz_maxprice)_DataCard1": {},
    "Max Price_DataCard1": {},
    "Maxprice_lbl": {},
    "MaxPrice_value": {},
    "Min Price (ntz_minprice)_DataCard1": {},
    "Min Price_DataCard1": {},
    "MinPrice_lbl": {},
    "MinPrice_value": {},
    "MinuteValue1": {},
    "MinuteValue2": {},
    "ModelDrivenFormIntegration": {
      "Data": {
        "Type": {
          "EnumString": "",
          "Kind": "Table",
          "Name": "Root",
          "Type": [
            {
              "EnumString": "",
              "Kind": "String",
              "Name": "ItemId",
              "Type": []
            },
            {
              "EnumString": "",
              "Kind": "DateTime",
              "Name": "RefreshedOn",
              "Type": []
            }
          ]
        },
        "Version": "1.326"
      }
    },
    "Name_DataCard1": {},
    "NonRefiil_CB": {},
    "Non-refill_lbl": {},
    "Prodcut_lbl": {},
    "Product _Code": {},
    "Productcode_lbl": {},
    "ProductList_CB": {},
    "Quantity_DataCard1": {},
    "Quantity_lbl": {},
    "Quantity_value": {},
    "SaveButton": {},
    "Screen_AddNewCustomerTargetPricing": {},
    "Screen_ViewCustomerTargetPricing": {},
    "Screen1": {},
    "Separator1": {},
    "Separator2": {},
    "Separator3": {},
    "StarVisible1": {},
    "StarVisible10": {},
    "StarVisible11": {},
    "StarVisible12": {},
    "StarVisible13": {},
    "StarVisible14": {},
    "StarVisible15": {},
    "StarVisible16": {},
    "StarVisible17": {},
    "StarVisible18": {},
    "StarVisible19": {},
    "StarVisible2": {},
    "StarVisible20": {},
    "StarVisible21": {},
    "StarVisible22": {},
    "StarVisible23": {},
    "StarVisible25": {},
    "StarVisible26": {},
    "StarVisible27": {},
    "StarVisible28": {},
    "StarVisible3": {},
    "StarVisible34": {},
    "StarVisible35": {},
    "StarVisible4": {},
    "StarVisible5": {},
    "StarVisible6": {},
    "StarVisible7": {},
    "StarVisible8": {},
    "StarVisible9": {},
    "TextInput1": {},
    "TextInput1_1": {},
    "TextInput1_2": {},
    "TextInput1_3": {},
    "TextInput1_4": {},
    "TextInput1_5": {},
    "TextInput1_6": {},
    "TextInput1_7": {},
    "TextInput12": {},
    "TextInput12_1": {},
    "TextInput13": {},
    "TextInput14": {},
    "TextInput15": {},
    "TextInput2": {},
    "TextInput3": {},
    "TextInput4": {},
    "TextInput5": {},
    "TextInput6": {},
    "TextInput7": {},
    "TextInput8": {},
    "Title_DataCard1": {},
    "Variant_DataCard1": {},
    "Variant_value": {},
    "Varient_label": {}
  },
  "PCFDynamicSchemaForIRRetrievalEntry": {
    "ModelDrivenFormIntegration": {}
  },
  "PublishOrderIndices": {
    "ABV_DataCard1": 145,
    "ABV_DataCard2": 197,
    "Add_Icon": 73,
    "ALC_lbl": 69,
    "ALC_value": 77,
    "App": 0,
    "Attachments_DataCard2": 102,
    "Barcode_DataCard1": 135,
    "Barcode_DataCard2": 202,
    "Bottle_DataCard1": 160,
    "Bottle_DataCard2": 207,
    "Btl/Ctn_DataCard1": 150,
    "Btl/Ctn_DataCard2": 212,
    "Button1": 180,
    "Button2": 2,
    "Button3": 3,
    "Button4": 107,
    "Carton_Quantity_vlaue": 74,
    "Checkbox1": 35,
    "Checkbox1_1": 37,
    "Checkbox2": 81,
    "Checkbox2_1": 82,
    "ComboBox1": 25,
    "Contact_DataCard1": 15,
    "Contact_DataCard2": 248,
    "Container3": 24,
    "CQ_Label": 70,
    "Create Date_DataCard1": 217,
    "Currency_lbl": 61,
    "Currency_value": 62,
    "Customer Lead Id_DataCard1": 12,
    "Customer Lead Id_DataCard2": 113,
    "Customer Lead Id_DataCard3": 253,
    "DataCardKey1": 16,
    "DataCardKey10": 214,
    "DataCardKey11": 218,
    "DataCardKey12": 222,
    "DataCardKey13": 230,
    "DataCardKey14": 235,
    "DataCardKey15": 115,
    "DataCardKey16": 128,
    "DataCardKey17": 120,
    "DataCardKey18": 132,
    "DataCardKey19": 152,
    "DataCardKey2": 184,
    "DataCardKey20": 147,
    "DataCardKey21": 137,
    "DataCardKey22": 162,
    "DataCardKey23": 172,
    "DataCardKey24": 157,
    "DataCardKey25": 167,
    "DataCardKey27": 240,
    "DataCardKey28": 245,
    "DataCardKey29": 250,
    "DataCardKey3": 189,
    "DataCardKey30": 255,
    "DataCardKey31": 142,
    "DataCardKey37": 99,
    "DataCardKey38": 104,
    "DataCardKey4": 13,
    "DataCardKey5": 22,
    "DataCardKey6": 194,
    "DataCardKey7": 199,
    "DataCardKey8": 204,
    "DataCardKey9": 209,
    "DataCardValue1": 185,
    "DataCardValue10": 236,
    "DataCardValue11": 241,
    "DataCardValue12": 246,
    "DataCardValue13": 251,
    "DataCardValue14": 116,
    "DataCardValue15": 122,
    "DataCardValue16": 133,
    "DataCardValue17": 153,
    "DataCardValue18": 148,
    "DataCardValue19": 138,
    "DataCardValue2": 190,
    "DataCardValue20": 163,
    "DataCardValue21": 173,
    "DataCardValue22": 158,
    "DataCardValue23": 168,
    "DataCardValue25": 256,
    "DataCardValue26": 143,
    "DataCardValue3": 195,
    "DataCardValue32": 100,
    "DataCardValue33": 105,
    "DataCardValue4": 200,
    "DataCardValue5": 205,
    "DataCardValue6": 210,
    "DataCardValue7": 215,
    "DataCardValue8": 219,
    "DataCardValue9": 231,
    "DateValue1": 23,
    "DateValue2": 129,
    "DateValue3": 223,
    "Decoded_CB": 57,
    "Decoded_Lbl": 54,
    "Description_DataCard1": 187,
    "Description_DataCard2": 118,
    "Edit_icon": 93,
    "ErrorMessage1": 186,
    "ErrorMessage10": 232,
    "ErrorMessage11": 237,
    "ErrorMessage12": 242,
    "ErrorMessage13": 117,
    "ErrorMessage14": 126,
    "ErrorMessage15": 121,
    "ErrorMessage16": 134,
    "ErrorMessage17": 154,
    "ErrorMessage18": 149,
    "ErrorMessage19": 139,
    "ErrorMessage2": 191,
    "ErrorMessage20": 164,
    "ErrorMessage21": 174,
    "ErrorMessage22": 159,
    "ErrorMessage23": 169,
    "ErrorMessage25": 247,
    "ErrorMessage26": 252,
    "ErrorMessage27": 257,
    "ErrorMessage28": 144,
    "ErrorMessage3": 196,
    "ErrorMessage34": 101,
    "ErrorMessage35": 106,
    "ErrorMessage4": 20,
    "ErrorMessage5": 201,
    "ErrorMessage6": 206,
    "ErrorMessage7": 211,
    "ErrorMessage8": 216,
    "ErrorMessage9": 227,
    "Expiry Date_DataCard1": 18,
    "Expiry Date_DataCard2": 123,
    "Expiry Date_DataCard3": 220,
    "Form1": 11,
    "Form2": 112,
    "Form3": 181,
    "Form5": 96,
    "Gallery1": 79,
    "Gallery2": 175,
    "galleryTemplate1": 80,
    "galleryTemplate2": 176,
    "Group1": 48,
    "Header Label_1": 6,
    "Header Label_2": 108,
    "Header_1": 7,
    "Home Screen": 3,
    "Home_Icon": 9,
    "Home_Icon_1": 110,
    "HourValue1": 224,
    "Icon1": 47,
    "Icon2": 178,
    "Icon2_1": 179,
    "Icon3": 94,
    "Image1": 0,
    "Image2": 1,
    "Image3": 5,
    "Image5": 109,
    "Item No_DataCard1": 130,
    "Item No_DataCard2": 192,
    "Label1": 4,
    "Label2": 26,
    "Label2_1": 28,
    "Label2_10": 45,
    "Label2_2": 30,
    "Label2_3": 32,
    "Label2_4": 34,
    "Label2_5": 36,
    "Label2_6": 38,
    "Label2_7": 40,
    "Label2_8": 42,
    "Label2_9": 44,
    "Label3": 78,
    "Label4": 52,
    "Label4_26": 49,
    "Label4_36": 50,
    "Label4_38": 51,
    "Label5": 177,
    "Label6": 111,
    "Label8": 10,
    "Litres_lbl": 71,
    "Litres_Value": 76,
    "Logo_1": 8,
    "Lt/Btl_DataCard1": 170,
    "Lt/Btl_DataCard2": 228,
    "Max Price (ntz_maxprice)_DataCard1": 233,
    "Max Price_DataCard1": 155,
    "Maxprice_lbl": 56,
    "MaxPrice_value": 66,
    "Min Price (ntz_minprice)_DataCard1": 238,
    "Min Price_DataCard1": 165,
    "MinPrice_lbl": 59,
    "MinPrice_value": 65,
    "MinuteValue1": 125,
    "MinuteValue2": 226,
    "ModelDrivenFormIntegration": 2,
    "Name_DataCard1": 182,
    "NonRefiil_CB": 58,
    "Non-refill_lbl": 53,
    "Prodcut_lbl": 55,
    "Product _Code": 75,
    "Productcode_lbl": 68,
    "ProductList_CB": 64,
    "Quantity_DataCard1": 140,
    "Quantity_lbl": 60,
    "Quantity_value": 63,
    "SaveButton": 95,
    "Screen_AddNewCustomerTargetPricing": 88,
    "Screen_ViewCustomerTargetPricing": 191,
    "Screen1": 10,
    "Separator1": 19,
    "Separator2": 124,
    "Separator3": 225,
    "StarVisible1": 183,
    "StarVisible10": 229,
    "StarVisible11": 234,
    "StarVisible12": 239,
    "StarVisible13": 114,
    "StarVisible14": 127,
    "StarVisible15": 119,
    "StarVisible16": 131,
    "StarVisible17": 151,
    "StarVisible18": 146,
    "StarVisible19": 136,
    "StarVisible2": 188,
    "StarVisible20": 161,
    "StarVisible21": 171,
    "StarVisible22": 156,
    "StarVisible23": 166,
    "StarVisible25": 244,
    "StarVisible26": 249,
    "StarVisible27": 254,
    "StarVisible28": 141,
    "StarVisible3": 193,
    "StarVisible34": 98,
    "StarVisible35": 103,
    "StarVisible4": 21,
    "StarVisible5": 198,
    "StarVisible6": 203,
    "StarVisible7": 208,
    "StarVisible8": 213,
    "StarVisible9": 221,
    "TextInput1": 27,
    "TextInput1_1": 29,
    "TextInput1_2": 31,
    "TextInput1_3": 33,
    "TextInput1_4": 39,
    "TextInput1_5": 41,
    "TextInput1_6": 43,
    "TextInput1_7": 46,
    "TextInput12": 89,
    "TextInput12_1": 88,
    "TextInput13": 90,
    "TextInput14": 91,
    "TextInput15": 92,
    "TextInput2": 83,
    "TextInput3": 14,
    "TextInput4": 17,
    "TextInput5": 84,
    "TextInput6": 85,
    "TextInput7": 86,
    "TextInput8": 87,
    "Title_DataCard1": 97,
    "Variant_DataCard1": 243,
    "Variant_value": 72,
    "Varient_label": 67
  },
  "ResourcesJsonIndices": {
    "Image-Bacardi-hpb": 1,
    "Image-Craft-Beer": 2,
    "Image-decorative-green-color-modern-geometric-stripes-transparent-background-vector_1055-12665 (1)": 3,
    "Image-download": 4,
    "Image-Kollaras_and_Co": 5,
    "Image-Mogul-Banner": 6,
    "Image-OIP": 8,
    "Image-OIP (5)": 7,
    "Image-Peroni": 9,
    "Image-SampleImage": 0
  },
  "RuleScreenIdWithoutScreen": {},
  "TemplateVersions": {},
  "VolatileProperties": {
    "AnalysisLoadTime": 2.21641,
    "ControlCount": {
      "attachments": 1,
      "button": 5,
      "checkbox": 6,
      "combobox": 9,
      "datepicker": 3,
      "dropdown": 3,
      "form": 4,
      "gallery": 2,
      "galleryTemplate": 2,
      "group": 2,
      "groupContainer": 1,
      "hostControl": 1,
      "icon": 8,
      "image": 5,
      "label": 128,
      "screen": 4,
      "text": 47,
      "typedDataCard": 32
    },
    "DeserializationLoadTime": 4.3674645,
    "ErrorCount": 2
  },
  "WasLocalDatabaseReferencesEmpty": false
}